setup.py
peerreach/__init__.py
peerreach/api.py
peerreach/parsers.py
peerreach/runner.py
peerreach.egg-info/PKG-INFO
peerreach.egg-info/SOURCES.txt
peerreach.egg-info/dependency_links.txt
peerreach.egg-info/entry_points.txt
peerreach.egg-info/requires.txt
peerreach.egg-info/top_level.txt