Metadata-Version: 1.1
Name: peerreach
Version: 0.2
Summary: Access peerreach api
Home-page: https://bitbucket.org/ferranp/peerreach
Author: Ferran Pegueroles Forcadell
Author-email: ferran@pegueroles.com
License: GPL
Download-URL: https://bitbucket.org/ferranp/loadcsv/downloads
Platform: UNKNOWN
Classifier: Development Status :: 4 - Beta
Classifier: Environment :: Console
Classifier: Intended Audience :: Developers
Classifier: Intended Audience :: Information Technology
Classifier: Intended Audience :: System Administrators
Classifier: License :: OSI Approved :: GNU General Public License (GPL)
Classifier: Programming Language :: Python
Classifier: Topic :: Internet
Classifier: Topic :: Utilities
Classifier: Topic :: Software Development
Classifier: Topic :: Software Development :: Libraries
